Workbook

Sheet 成本总览
A1: RK3506B + 512MB + 2GB eMMC + 双频 WiFi 智能采集终端成本预估
A2: 口径：保留 100 台试产和 1000 台量产两档；包含有线网与 WiFi；PCBA 与整机分开；不含税、模具、认证、研发 NRE 和软件许可。
A4: 方案 | B4: 单台成本 RMB | C4: 说明 | E4: 关键结论 | F4: 典型值
A5: PCBA（100台试产） | B5: =SUM(典型BOM!$F$5:$F$23) | C5: 主板、接口、WiFi、电源、PCB、贴片和基础测试 | E5: 100台整机 | F5: =B6
A6: 整机（100台试产） | B6: =SUM(典型BOM!$F$5:$F$26) | C6: PCBA + 简易外壳 + 5V电源/USB线 + 装配老化包装 | E6: 1000台整机 | F6: =B8
A7: PCBA（1000台量产） | B7: =SUM(典型BOM!$H$5:$H$23) | C7: 按稳定供应链与批量制造的单台目标值 | E7: WiFi子系统（100台） | F7: =SUM(典型BOM!F8:F9)+典型BOM!F13
A8: 整机（1000台量产） | B8: =SUM(典型BOM!$H$5:$H$26) | C8: 不含模具摊销、税费、认证和售后备件 | E8: 主平台（100台） | F8: =SUM(典型BOM!F5:F7)
A10: 成本拆分 | B10: 100台 RMB | C10: 1000台 RMB
A11: 核心平台 | B11: =SUM(典型BOM!F5:F7) | C11: =SUM(典型BOM!H5:H7) | D11: RK3506B + 512MB DDR3L + 2GB eMMC
A12: WiFi | B12: =SUM(典型BOM!F8:F9)+典型BOM!F13 | C12: =SUM(典型BOM!H8:H9)+典型BOM!H13 | D12: 双频 WiFi 5 模组、天线和 Host 供电/ESD
A13: 有线网络 | B13: =SUM(典型BOM!F10:F11) | C13: =SUM(典型BOM!H10:H11) | D13: 100M PHY + 带变压器 RJ45
A14: USB Gadget | B14: =典型BOM!F12 | C14: =典型BOM!H12 | D14: MSC/Printer 专用 USB Device 接口及防倒灌
A15: 电源/基础器件 | B15: =SUM(典型BOM!F14:F20) | C15: =SUM(典型BOM!H14:H20) | D15: 电源、无源、RTC、状态件、接口保护和连接器
A16: PCB/制造 | B16: =SUM(典型BOM!F21:F23) | C16: =SUM(典型BOM!H21:H23) | D16: 6层PCB、BGA贴片、X-Ray、测试和损耗
A17: 整机增量 | B17: =SUM(典型BOM!F24:F26) | C17: =SUM(典型BOM!H24:H26) | D17: 外壳、电源线材、装配老化和包装
A19: 注意：2GB eMMC 只适合精简 Linux、单 rootfs 和严格自动清理；若保留 512MB MSC 镜像或缓存较多报告，建议改为 4GB/8GB。2GB 小容量料不一定比 8GB 更易采购。

Sheet 典型BOM
A1: RK3506B + 512MB + 2GB eMMC + 双频 WiFi 智能采集终端 BOM 成本
A2: 价格单位：人民币元；100台/1000台均为工程估算，不是锁价报价；基础方案保留 100M Ethernet、双频 WiFi 和 USB MSC/Printer Gadget。
A4: 分类 | B4: 物料/模块 | C4: 建议型号/规格 | D4: 数量 | E4: 100台单价 | F4: 100台小计 | G4: 1000台单价 | H4: 1000台小计 | I4: 备注
A5: 核心平台 | B5: 主控 SoC | C5: Rockchip RK3506B / FBGA-333 | D5: 1 | E5: 21 | F5: =D5*E5 | G5: 18 | H5: =D5*G5 | I5: 公开预订参考价约20.91元；量产以代理正式报价为准
A6: 内存 | B6: DDR3L | C6: 512MB DDR3L，16-bit | D6: 1 | E6: 18 | F6: =D6*E6 | G6: 12 | H6: =D6*G6 | I6: 完整 Python + GhostPCL 的最低建议内存
A7: 存储 | B7: eMMC | C7: 2GB eMMC | D7: 1 | E7: 15 | F7: =D7*E7 | G7: 11 | H7: =D7*G7 | I7: 低容量料需确认生命周期；同时询4GB/8GB报价
A8: WiFi | B8: 双频无线模组 | C8: USB 2.0 WiFi 5，2.4G/5G，1T1R | D8: 1 | E8: 28 | F8: =D8*E8 | G8: 20 | H8: =D8*G8 | I8: 选固定芯片和长期Linux驱动，不使用随机白牌网卡
A9: WiFi | B9: 天线/射频辅料 | C9: IPEX/MHF4 双频天线 + 同轴线 | D9: 1 | E9: 6 | F9: =D9*E9 | G9: 4 | H9: =D9*G9 | I9: 最终外壳内做RSSI与EMC验证
A10: 有线网络 | B10: 以太网 PHY | C10: 10/100M RMII PHY | D10: 1 | E10: 7 | F10: =D10*E10 | G10: 5 | H10: =D10*G10 | I10: Ethernet优先，WiFi作为移动部署和回退链路
A11: 有线网络 | B11: RJ45 网络座 | C11: 10/100M 带网络变压器和指示灯 | D11: 1 | E11: 8 | F11: =D11*E11 | G11: 6 | H11: =D11*G11 | I11: 含基础网口器件，不含网线
A12: USB Gadget | B12: Device接口与保护 | C12: USB-C/B、ESD、CC/VBUS检测、防倒灌 | D12: 1 | E12: 10 | F12: =D12*E12 | G12: 7 | H12: =D12*G12 | I12: 专用于MSC/Printer模式切换
A13: WiFi | B13: USB Host供电/ESD | C13: 第二路OTG Host、负载开关、ESD | D13: 1 | E13: 8 | F13: =D13*E13 | G13: 5 | H13: =D13*G13 | I13: WiFi与Gadget分开控制器；无需Hub时按本项估算
A14: 电源 | B14: PMIC/DC-DC/LDO | C14: 5V输入，DDR/Core/3.3V电源轨 | D14: 1 | E14: 20 | F14: =D14*E14 | G14: 13 | H14: =D14*G14 | I14: 含基础稳压滤波，不含外置5V适配器
A15: 基础器件 | B15: 晶振/无源器件 | C15: 时钟、电阻、电容、电感及去耦 | D15: 1 | E15: 15 | F15: =D15*E15 | G15: 10 | H15: =D15*G15 | I15: 按直接SoC板工程中值
A16: 调试维护 | B16: UART/烧录测试点 | C16: 3.3V UART、Recovery、量产测试点 | D16: 1 | E16: 4 | F16: =D16*E16 | G16: 2 | H16: =D16*G16 | I16: 量产可只保留焊盘
... A26: 整机 | B26: 装配/老化/包装 | C26: 整机装配、基础老化、包装 | D26: 1 | E26: 28 | F26: =D26*E26 | G26: 16 | H26: =D26*G26 | I26: 不含售后备件和物流

Sheet 假设说明
A1: RK3506 成本估算假设和维护说明
A3: 项目 | B3: 内容 | C3: 影响 | D3: 维护建议
A4: 价格口径 | B4: 100台按小批量采购/打样中值，1000台按稳定供应链目标值。 | C4: 不是锁价报价，存储和模组价格会波动。 | D4: 立项后向两家以上供应商询价并替换BOM单价。
A5: 功能范围 | B5: 保留100M Ethernet、双频WiFi、USB MSC/Printer Gadget、HTTPS管理和报告上传。 | C5: 不是单纯Linux最小板，USB保护和制造测试不能省略。 | D5: 删减功能时同时更新BOM、原理图和验证清单。
A6: 内存 | B6: 512MB为当前Python、SQLite、Pillow和单任务GhostPCL的最低建议值。 | C6: 并行转换或大页PCL可能出现内存压力。 | D6: 限制为单转换worker，记录峰值RSS；不足时改1GB。
A7: 2GB eMMC | B7: 按精简Linux、单rootfs、无桌面、严格日志/报告清理估算。 | C7: 若MSC镜像为512MB，剩余报告缓存和升级空间很小。 | D7: 优先把MSC镜像降到256MB；同时询4GB/8GB价格。
A8: WiFi | B8: 双频WiFi 5通过RK3506第二路USB OTG/Host连接，第一路专用于Gadget。 | C8: 避免无线重连影响MSC/Printer重新枚举。 | D8: 冻结模组芯片、驱动和固件，做弱信号/重连/EMC测试。
A9: 网络策略 | B9: Ethernet优先，WiFi回退；两条链路都支持DHCP，配置可选静态IP。 | C9: 网络切换时上传任务必须持久化。 | D9: 做拔网线、AP重启和断网恢复测试。
A10: 不包含项 | B10: 税费、物流、模具、认证、医疗级隔离/电源、GhostPDL商业许可、研发NRE、服务器费用。 | C10: 这些费用会影响项目总投入和销售成本。 | D10: 项目立项时另建NRE和认证费用表。
A11: 制造成本 | B11: PCB、BGA贴片、X-Ray和测试按当前数量级工程中值估算。 | C11: 板层、尺寸、良率和工装会改变单价。 | D11: Gerber/BOM冻结后向PCBA厂重新报价。
A12: 维护方式 | B12: 在典型BOM中修改100台/1000台单价，总览公式自动更新。 | C12: 便于后续比较2GB、4GB、8GB和不同WiFi模组。 | D12: 不要手工覆盖成本总览中的公式。
A14: 器件资料页（用于确认定位和公开参考价，不是量产采购报价）
A15: 器件 | B15: 资料页 URL | C15: 用途 | D15: 说明
A16: RK3506 官方页 | B16: https://www.rock-chips.com/a/en/products/RK35_Series/2025/1208/2126.html | C16: SoC规格 | D16: 确认三核A7、双USB OTG和外置DDR接口
A17: RK3506B 价格页 | B17: https://www.jlc-smt.com/lcsc/detail/C48642328.html | C17: 公开价格参考 | D17: 2026-07-16页面预订参考价20.91元/PCS，库存和量产价另询
A18: Core3506 | B18: https://www.waveshare.com/product/core3506.htm | C18: 核心板参考 | D18: 确认512MB DDR3L、双USB OTG和8GB eMMC选项
A19: 项目设计规格 | B19: docs/RK3506_VS_T113_REPORT_GATEWAY.md | C19: 本项目架构 | D19: 确认WiFi、USB Gadget和成本口径
